lichessbot/__init__.py
lichessbot/config.py
lichessbot/conversation.py
lichessbot/engine_wrapper.py
lichessbot/lichess.py
lichessbot/lichessbot_main.py
lichessbot/logging_pool.py
lichessbot/model.py
lichessbot/resources.py
lichessbot-1.1.0.dist-info/DESCRIPTION.rst
lichessbot-1.1.0.dist-info/METADATA
lichessbot-1.1.0.dist-info/RECORD
lichessbot-1.1.0.dist-info/WHEEL
lichessbot-1.1.0.dist-info/entry_points.txt
lichessbot-1.1.0.dist-info/metadata.json
lichessbot-1.1.0.dist-info/top_level.txt
